pymerdoc/__init__.py
pymerdoc/gm.py
pymerdoc/main.py
pymerdoc/mc.py
pymerdoc/theme_manager.py
tests/__init__.py
tests/conftest.py
tests/test_basic.py
tests/test_markdown.py
pymerdoc-0.2.0.dist-info/METADATA
pymerdoc-0.2.0.dist-info/WHEEL
pymerdoc-0.2.0.dist-info/entry_points.txt
pymerdoc-0.2.0.dist-info/top_level.txt
pymerdoc-0.2.0.dist-info/RECORD
