Metadata-Version: 2.1
Name: pymerdoc
Version: 0.2.0
Summary: A tool for creating and managing Mermaid diagrams with modern UI
Home-page: https://github.com/scottpeterman/pymerdoc
Author: Scott Peterman
Author-email: scottpeterman@example.com
Project-URL: Bug Reports, https://github.com/scottpeterman/pymerdoc/issues
Project-URL: Source, https://github.com/scottpeterman/pymerdoc
Classifier: Development Status :: 3 - Alpha
Classifier: Intended Audience :: Developers
Classifier: License :: OSI Approved :: GNU General Public License v3 (GPLv3)
Classifier: Operating System :: OS Independent
Classifier: Programming Language :: Python :: 3
Classifier: Programming Language :: Python :: 3.8
Classifier: Programming Language :: Python :: 3.9
Classifier: Programming Language :: Python :: 3.10
Classifier: Programming Language :: Python :: 3.11
Classifier: Topic :: Software Development :: Documentation
Classifier: Topic :: Software Development :: Libraries :: Python Modules
Requires-Python: >=3.8
Requires-Dist: colorama>=0.4.6
Requires-Dist: exceptiongroup>=1.2.2
Requires-Dist: importlib_metadata>=8.5.0
Requires-Dist: iniconfig>=2.0.0
Requires-Dist: Markdown>=3.7
Requires-Dist: packaging>=24.2
Requires-Dist: pillow>=11.0.0
Requires-Dist: pluggy>=1.5.0
Requires-Dist: PyQt6>=6.8.0
Requires-Dist: PyQt6-Qt6>=6.8.1
Requires-Dist: PyQt6-WebEngine>=6.8.0
Requires-Dist: PyQt6-WebEngine-Qt6>=6.8.1
Requires-Dist: PyQt6_sip>=13.9.1
Requires-Dist: pytest>=8.3.4
Requires-Dist: pytest-qt>=4.4.0
Requires-Dist: tomli>=2.2.1
Requires-Dist: zipp>=3.21.0
